setup.py
generalDistributions/Binomialdistribution.py
generalDistributions/Gaussiandistribution.py
generalDistributions/Generaldistribution.py
generalDistributions/__init__.py
generalDistributions.egg-info/PKG-INFO
generalDistributions.egg-info/SOURCES.txt
generalDistributions.egg-info/dependency_links.txt
generalDistributions.egg-info/not-zip-safe
generalDistributions.egg-info/top_level.txt