Metadata-Version: 1.0
Name: generalDistributions
Version: 0.2
Summary: Gaussian distributions
Home-page: UNKNOWN
Author: abdelwahid benzerrouk
Author-email: benzerrouk.wahid@gmail.com
License: UNKNOWN
Platform: UNKNOWN
